examples/__init__.py
examples/project_import_export.py
examples/advanced/__init__.py
examples/advanced/additional_learning.py
examples/advanced/evo_operators_comparison.py
examples/advanced/gpu_example.py
examples/advanced/multi_modal_pipeline.py
examples/advanced/multimodal_text_num_example.py
examples/advanced/multiobj_optimisation.py
examples/advanced/multitask_classification_regression.py
examples/advanced/parallelization_comparison.py
examples/advanced/pipeline_sensitivity.py
examples/advanced/profiler_example.py
examples/advanced/surrogate_optimization.py
examples/advanced/automl/__init__.py
examples/advanced/automl/h2o_example.py
examples/advanced/automl/pipeline_from_automl.py
examples/advanced/automl/tpot_example.py
examples/advanced/automl/tpot_vs_fedot.py
examples/advanced/decompose/__init__.py
examples/advanced/decompose/classification_refinement_example.py
examples/advanced/decompose/refinement_forecast_example.py
examples/advanced/decompose/regression_refinement_example.py
examples/advanced/fedot_based_solutions/__init__.py
examples/advanced/fedot_based_solutions/external_optimizer.py
examples/advanced/remote_execution/__init__.py
examples/advanced/remote_execution/remote_fit_example.py
examples/advanced/remote_execution/ts_composer_with_integration.py
examples/advanced/structural_analysis/__init__.py
examples/advanced/structural_analysis/complex_analysis_with_requirements.py
examples/advanced/structural_analysis/dataset_access.py
examples/advanced/structural_analysis/pipelines_access.py
examples/advanced/structural_analysis/structural_analysis_example.py
examples/advanced/time_series_forecasting/__init__.py
examples/advanced/time_series_forecasting/composing_pipelines.py
examples/advanced/time_series_forecasting/custom_model_tuning.py
examples/advanced/time_series_forecasting/exogenous.py
examples/advanced/time_series_forecasting/multi_ts_arctic_forecasting.py
examples/advanced/time_series_forecasting/multistep.py
fedot-0.7.5.dist-info/LICENSE.md
fedot-0.7.5.dist-info/METADATA
fedot-0.7.5.dist-info/WHEEL
fedot-0.7.5.dist-info/top_level.txt
fedot-0.7.5.dist-info/RECORD
