Metadata-Version: 2.1
Name: fedot
Version: 0.7.5
Summary: Automated machine learning framework for composite pipelines
Home-page: https://github.com/aimclub/FEDOT
Author: NSS Lab
Author-email: itmo.nss.team@gmail.com
License: BSD 3-Clause
Classifier: License :: OSI Approved :: BSD License
Classifier: Programming Language :: Python :: 3.8
Classifier: Programming Language :: Python :: 3.9
Classifier: Programming Language :: Python :: 3.10
Requires-Python: >=3.8
License-File: LICENSE.md
Requires-Dist: scipy<1.13.0
Requires-Dist: thegolem==0.4.1
Requires-Dist: numpy!=1.24.0,>=1.16.0
Requires-Dist: anytree>=2.8.0
Requires-Dist: catboost>=0.25.0
Requires-Dist: lightgbm>=3.0.0
Requires-Dist: xgboost>=1.4.0
Requires-Dist: statsmodels>=0.12.0
Requires-Dist: ete3>=3.1.0
Requires-Dist: networkx!=2.7.*,!=2.8.1,!=2.8.2,!=2.8.3,>=2.4
Requires-Dist: hyperopt==0.2.7
Requires-Dist: SALib>=1.3.0
Requires-Dist: scikit-optimize>=0.7.4
Requires-Dist: pyvis==0.2.1
Requires-Dist: seaborn>=0.9.0
Requires-Dist: func-timeout==4.3.5
Requires-Dist: joblib>=0.17.0
Requires-Dist: requests>=2.0
Requires-Dist: typing>=3.7.0
Requires-Dist: psutil>=5.9.2
Requires-Dist: pytest>=6.2.0
Requires-Dist: testfixtures>=6.18.0
Requires-Dist: sktime==0.16.1; python_version < "3.10"
Requires-Dist: sktime>=0.16.1; python_version >= "3.10"
Requires-Dist: pandas>=1.3.0; python_version >= "3.8"
Requires-Dist: scikit-learn<1.6,>=1.0.0; python_version >= "3.8"
Requires-Dist: matplotlib>=3.3.1; python_version >= "3.8"
Provides-Extra: docs
Requires-Dist: sphinx==4.2.0; extra == "docs"
Requires-Dist: sphinx-rtd-theme==1.0.0; extra == "docs"
Requires-Dist: readthedocs-sphinx-search==0.3.2; extra == "docs"
Requires-Dist: sphinxcontrib-details-directive; extra == "docs"
Requires-Dist: autodocsumm; extra == "docs"
Provides-Extra: examples
Requires-Dist: openpyxl==3.0.7; extra == "examples"
Provides-Extra: extra
Requires-Dist: torch>=1.9.0; extra == "extra"
Requires-Dist: opencv-python>=4.5.5.64; extra == "extra"
Requires-Dist: Pillow>=8.2.0; extra == "extra"
Requires-Dist: gensim==4.3.2; extra == "extra"
Requires-Dist: nltk==3.8.1; extra == "extra"
Requires-Dist: protobuf~=3.19.0; extra == "extra"
Requires-Dist: giotto-tda==0.6.0; extra == "extra"
Requires-Dist: ripser==0.6.4; extra == "extra"
Requires-Dist: tensorflow>=2.8.0; python_version >= "3.8" and extra == "extra"
Provides-Extra: profilers
Requires-Dist: snakeviz==2.1.0; extra == "profilers"
Requires-Dist: gprof2dot==2021.2.21; extra == "profilers"
Requires-Dist: objgraph==3.5.0; extra == "profilers"
Requires-Dist: memory-profiler==0.58.0; extra == "profilers"
